LICENSE
MANIFEST.in
README.md
setup.py
OASYS1_XRT.egg-info/PKG-INFO
OASYS1_XRT.egg-info/SOURCES.txt
OASYS1_XRT.egg-info/dependency_links.txt
OASYS1_XRT.egg-info/entry_points.txt
OASYS1_XRT.egg-info/namespace_packages.txt
OASYS1_XRT.egg-info/not-zip-safe
OASYS1_XRT.egg-info/requires.txt
OASYS1_XRT.egg-info/top_level.txt
orangecontrib/__init__.py
orangecontrib/xrt/__init__.py
orangecontrib/xrt/util/__init__.py
orangecontrib/xrt/util/toroid_mirror_distorted.py
orangecontrib/xrt/util/xrt_data.py
orangecontrib/xrt/widgets/__init__.py
orangecontrib/xrt/widgets/beamline_elements/__init__.py
orangecontrib/xrt/widgets/beamline_elements/ow_double_paraboloid_lens.py
orangecontrib/xrt/widgets/beamline_elements/ow_plate.py
orangecontrib/xrt/widgets/beamline_elements/ow_rectangular_aperture.py
orangecontrib/xrt/widgets/beamline_elements/ow_screen.py
orangecontrib/xrt/widgets/beamline_elements/ow_toroid_mirror_distorted.py
orangecontrib/xrt/widgets/beamline_elements/icons/beam_stopper.png
orangecontrib/xrt/widgets/beamline_elements/icons/beamline_elements.png
orangecontrib/xrt/widgets/beamline_elements/icons/crl.png
orangecontrib/xrt/widgets/beamline_elements/icons/crystal.png
orangecontrib/xrt/widgets/beamline_elements/icons/filter.png
orangecontrib/xrt/widgets/beamline_elements/icons/grating.png
orangecontrib/xrt/widgets/beamline_elements/icons/ideal_lens.png
orangecontrib/xrt/widgets/beamline_elements/icons/mirror.png
orangecontrib/xrt/widgets/beamline_elements/icons/screen.png
orangecontrib/xrt/widgets/beamline_elements/icons/slit.png
orangecontrib/xrt/widgets/beamline_elements/icons/toroidal_mirror.png
orangecontrib/xrt/widgets/gui/__init__.py
orangecontrib/xrt/widgets/gui/ow_optical_element.py
orangecontrib/xrt/widgets/gui/python_script.py
orangecontrib/xrt/widgets/gui/show_image_error_data_file_dialog.py
orangecontrib/xrt/widgets/light_sources/__init__.py
orangecontrib/xrt/widgets/light_sources/ow_undulator_light_source.py
orangecontrib/xrt/widgets/light_sources/icons/bm.png
orangecontrib/xrt/widgets/light_sources/icons/light_sources.png
orangecontrib/xrt/widgets/light_sources/icons/undulator.png
orangecontrib/xrt/widgets/light_sources/icons/wiggler.png
orangecontrib/xrt/widgets/tools/__init__.py
orangecontrib/xrt/widgets/tools/ow_xrt_runner.py
