Metadata-Version: 2.1
Name: OASYS1-XRT
Version: 0.0.3
Summary: XRT
Home-page: https://github.com/oasys-esrf-kit/OASYS1-XRT
Download-URL: https://github.com/oasys-esrf-kit/OASYS1-XRT
Author: Manuel Sanchez del Rio
Author-email: srio@esrf.eu
License: MIT
Keywords: simulator,oasys1
Classifier: Development Status :: 4 - Beta
Classifier: Environment :: X11 Applications :: Qt
Classifier: Environment :: Console
Classifier: Environment :: Plugins
Classifier: Programming Language :: Python :: 3
Classifier: Intended Audience :: Science/Research
License-File: LICENSE
Requires-Dist: oasys1>=1.2.131
Requires-Dist: syned-gui>=1.0.3
Requires-Dist: xrt
